pdf_hunter/__init__.py
pdf_hunter/search.py
pdf_hunter/url_transforms.py
pdf_hunter-0.1.6.dist-info/LICENSE
pdf_hunter-0.1.6.dist-info/METADATA
pdf_hunter-0.1.6.dist-info/WHEEL
pdf_hunter-0.1.6.dist-info/top_level.txt
pdf_hunter-0.1.6.dist-info/RECORD
