Metadata-Version: 2.1
Name: pdf-hunter
Version: 0.1.6
Summary: Download PDF links from a webpage
Home-page: UNKNOWN
Author: Simon Garisch
Author-email: gatman946@gmail.com
License: MIT
Platform: UNKNOWN
Requires-Dist: requests (>=2.22.0)
Requires-Dist: beautifulsoup4 (>=4.8.1)
